{"name":"Daisy 国货之光", "description":"校长图标TG @PVSZforQuanX", "icons":[{"name":"001.png", "url":"https:\/\/raw.githubusercontent.com\/shoujiqiyuan\/DaisyforQuanX\/master\/IconSet\/001.png"}, {"name":"002.png", "url":"https:\/\/raw.githubusercontent.com\/shoujiqiyuan\/DaisyforQuanX\/master\/IconSet\/002.png"}, {"name":"003.png", "url":"https:\/\/raw.githubusercontent.com\/shoujiqiyuan\/DaisyforQuanX\/master\/IconSet\/003.png"}, {"name":"004.png", "url":"https:\/\/raw.githubusercontent.com\/shoujiqiyuan\/DaisyforQuanX\/master\/IconSet\/004.png"}, {"name":"005.png", "url":"https:\/\/raw.githubusercontent.com\/shoujiqiyuan\/DaisyforQuanX\/master\/IconSet\/005.png"}, {"name":"006.png", "url":"https:\/\/raw.githubusercontent.com\/shoujiqiyuan\/DaisyforQuanX\/master\/IconSet\/006.png"}]}